eazyapi/__init__.py
eazyapi/__version__.py
eazyapi/base.py
eazyapi/delete.py
eazyapi/exceptions.py
eazyapi/get.py
eazyapi/main.py
eazyapi/patch.py
eazyapi/post.py
eazyapi/session.py
eazyapi/settings.py
eazyapi/includes/__init__.py
eazyapi/tests/__init__.py
eazyapi/tests/contract/__init__.py
eazyapi/tests/contract/get_contract.py
eazyapi/tests/contract/patch_contract.py
eazyapi/tests/contract/post_contract.py
eazyapi/tests/customer/__init__.py
eazyapi/tests/customer/get_customer.py
eazyapi/tests/customer/patch_customer.py
eazyapi/tests/customer/post_customer.py
eazyapi/tests/customer/psot_customer.py
eazyapi/tests/direct_debit/__init__.py
eazyapi/tests/direct_debit/archive.py
eazyapi/tests/direct_debit/cancel.py
eazyapi/tests/direct_debit/reactivate.py
eazyapi/tests/direct_debit/restart.py
eazyapi/tests/payment/__init__.py
eazyapi/tests/payment/delete_payment.py
eazyapi/tests/payment/get_payment.py
eazyapi/tests/payment/patch_payment.py
eazyapi/tests/payment/post_payment.py
eazyapi/tests/utils/__init__.py
eazyapi/tests/utils/schedules.py
eazyapi/tests/utils/working_days.py
eazyapi/utils/__init__.py
eazyapi/utils/contract_checks.py
eazyapi/utils/customer_checks.py
eazyapi/utils/payment_checks.py
eazyapi/utils/schedules.py
eazyapi/utils/working_days.py
eazysdk-1.3.0.dist-info/LICENSE
eazysdk-1.3.0.dist-info/METADATA
eazysdk-1.3.0.dist-info/WHEEL
eazysdk-1.3.0.dist-info/top_level.txt
eazysdk-1.3.0.dist-info/RECORD
