Metadata-Version: 2.1
Name: eazysdk
Version: 1.3.0
Summary: A Python SDK client to interact with Eazy Customer Manager 3
Home-page: https://github.com/EazyCollectServices/EazyCollectSDK-Python
Author: Eazy Collect
Author-email: help@eazycollect.co.uk
Classifier: Programming Language :: Python :: 3
Classifier: License :: OSI Approved :: MIT License
Classifier: Operating System :: OS Independent
License-File: LICENSE
